{
  "$id": "1",
  "$type": "Kingmaker.Blueprints.Classes.BlueprintFeature, Assembly-CSharp",
  "Groups": [],
  "Ranks": 1,
  "ReapplyOnLevelUp": false,
  "HideInUI": false,
  "m_AllowNonContextActions": false,
  "m_DisplayName": "LocalizedString::Quarry",
  "m_Description": "LocalizedString::At 11th level, a ran...",
  "m_Icon": {
    "$type": "Sprite",
    "name": "Command",
    "InstanceId": 53576
  },
  "Components": [
    {
      "$id": "2",
      "$type": "Kingmaker.Designers.Mechanics.Facts.RecommendedClass, Assembly-CSharp",
      "FavoriteClass": "Blueprint:cda0615668a6df14eb36ba19ee881af6:RangerClass",
      "name": "$RecommendedClass$3a3896b4-48d4-4781-a09a-445838d08c08"
    },
    {
      "$id": "3",
      "$type": "Kingmaker.UnitLogic.FactLogic.AddFacts, Assembly-CSharp",
      "Facts": [
        "Blueprint:e93dfca6f025e6d4e9583e688c147aca:QuarryAbility"
      ],
      "name": "$AddFacts$771c9b11-100a-416c-8c14-9addef5b283c"
    }
  ],
  "m_AssetGuid": "385260ca07d5f1b4e907ba22a02944fc",
  "name": "Quarry"
}